pewtils/__init__.py
pewtils/general_link_shorteners.csv
pewtils/http.py
pewtils/io.py
pewtils/regex.py
pewtils/vanity_link_shorteners.csv
tests/files/__init__.py
tests/files/py.py
tests/files/subfolder/__init__.py
tests/files/subfolder/subfolder_py.py
pewtils-1.1.5.dist-info/LICENSE
pewtils-1.1.5.dist-info/METADATA
pewtils-1.1.5.dist-info/WHEEL
pewtils-1.1.5.dist-info/top_level.txt
pewtils-1.1.5.dist-info/RECORD
