Metadata-Version: 2.1
Name: pewtils
Version: 1.1.5
Summary: General programming utilities from Pew Research Center
Home-page: https://github.com/pewresearch/pewtils
Author: Pew Research Center
Author-email: info@pewresearch.org
License: GPLv2+
Keywords: utilities,link standardization,input,output
Platform: UNKNOWN
Classifier: Development Status :: 5 - Production/Stable
Classifier: Environment :: Console
Classifier: Intended Audience :: Developers
Classifier: Intended Audience :: Education
Classifier: Intended Audience :: Information Technology
Classifier: Intended Audience :: Science/Research
Classifier: License :: OSI Approved :: GNU General Public License v2 or later (GPLv2+)
Classifier: Operating System :: OS Independent
Classifier: Programming Language :: Python :: 3.7
Classifier: Programming Language :: Python :: 3.8
Classifier: Programming Language :: Python :: 3.9
Classifier: Programming Language :: Python
Classifier: Topic :: Software Development :: Libraries :: Python Modules
Classifier: Topic :: Utilities
License-File: LICENSE
Requires-Dist: Unidecode (>=1.1.1)
Requires-Dist: beautifulsoup4 (>=4.10.0)
Requires-Dist: boto (>=2.49.0)
Requires-Dist: chardet (>=4.0.0)
Requires-Dist: fake-useragent (>=0.1.11)
Requires-Dist: lxml (>=4.4.2)
Requires-Dist: nilsimsa (>=0.3.8)
Requires-Dist: numpy (>=1.18.1)
Requires-Dist: pandas (>=0.25.3)
Requires-Dist: requests (>=2.25.1)
Requires-Dist: scandir (>=1.10.0)
Requires-Dist: six (>=1.16.0)
Requires-Dist: ssdeep (>=3.4)
Requires-Dist: stopit (>=1.1.2)
Requires-Dist: tldextract (>=2.2.2)
Requires-Dist: zipcodes (>=1.1.0)
